reporter/__init__.py
reporter/grafeas.py
reporter/sarif.py
reporter/utils.py
reporter/templates/base.html
reporter/templates/dep-report.html
reporter/templates/sast-report.html
test/__init__.py
test/test_sarif.py
appthreat_scan_reports-1.0.1.dist-info/METADATA
appthreat_scan_reports-1.0.1.dist-info/WHEEL
appthreat_scan_reports-1.0.1.dist-info/top_level.txt
appthreat_scan_reports-1.0.1.dist-info/RECORD
